{
  "game_id": "game_5523",
  "board_size": 9,
  "start_time": "2025-07-27T07:48:39.219981",
  "end_time": "2025-07-27T07:48:39.403069",
  "total_time": 0.18297600746154785,
  "total_moves": 64,
  "winner": "Player.black",
  "margin": 2.5,
  "moves": [
    "(r 3, c 7)",
    "(r 7, c 7)",
    "(r 4, c 7)",
    "(r 5, c 7)",
    "(r 2, c 7)",
    "(r 2, c 5)",
    "(r 2, c 6)",
    "(r 4, c 8)",
    "(r 5, c 8)",
    "(r 5, c 9)",
    "(r 6, c 8)",
    "(r 1, c 5)",
    "(r 5, c 6)",
    "(r 6, c 7)",
    "(r 6, c 9)",
    "(r 4, c 9)",
    "(r 8, c 3)",
    "(r 7, c 8)",
    "(r 6, c 5)",
    "(r 7, c 9)",
    "(r 5, c 4)",
    "(r 5, c 8)",
    "(r 4, c 4)",
    "(r 3, c 4)",
    "(r 3, c 3)",
    "(r 4, c 3)",
    "(r 5, c 3)",
    "(r 4, c 2)",
    "(r 5, c 2)",
    "(r 3, c 2)",
    "(r 2, c 2)",
    "(r 7, c 6)",
    "(r 6, c 2)",
    "(r 9, c 5)",
    "(r 5, c 5)",
    "(r 7, c 4)",
    "(r 3, c 6)",
    "(r 3, c 5)",
    "(r 7, c 2)",
    "(r 3, c 8)",
    "(r 2, c 8)",
    "(r 1, c 3)",
    "(r 2, c 9)",
    "(r 1, c 2)",
    "(r 1, c 8)",
    "(r 8, c 2)",
    "(r 9, c 2)",
    "(r 9, c 3)",
    "(r 9, c 4)",
    "(r 8, c 4)",
    "(r 9, c 3)",
    "(r 6, c 4)",
    "(r 7, c 3)",
    "(r 1, c 4)",
    "(r 4, c 3)",
    "(r 2, c 3)",
    "(r 2, c 4)",
    "(r 3, c 9)",
    "(r 2, c 3)",
    "(r 6, c 3)",
    "(r 2, c 5)",
    "(r 6, c 6)",
    "pass",
    "pass"
  ],
  "move_times": [
    0.00027680397033691406,
    0.0006682872772216797,
    0.005738019943237305,
    0.0059337615966796875,
    0.0006010532379150391,
    0.0064890384674072266,
    0.0006449222564697266,
    0.006644010543823242,
    0.004973173141479492,
    0.0013930797576904297,
    0.0002460479736328125,
    0.006290912628173828,
    0.005823850631713867,
    0.0002689361572265625,
    0.0055751800537109375,
    0.00023603439331054688,
    0.005326986312866211,
    0.006632089614868164,
    0.005224943161010742,
    0.00043320655822753906,
    0.0045621395111083984,
    0.002790212631225586,
    0.004609107971191406,
    0.007398843765258789,
    0.004900932312011719,
    0.007624149322509766,
    0.004769086837768555,
    0.0002789497375488281,
    0.00115203857421875,
    0.0031900405883789062,
    0.00046706199645996094,
    0.007375955581665039,
    0.0017399787902832031,
    0.0028259754180908203,
    0.003525972366333008,
    0.004239797592163086,
    0.0007219314575195312,
    0.00028824806213378906,
    0.0026128292083740234,
    0.0034050941467285156,
    0.0002918243408203125,
    0.003145933151245117,
    0.00090789794921875,
    0.002832174301147461,
    0.0008971691131591797,
    0.0027227401733398438,
    0.0004563331604003906,
    0.002607107162475586,
    0.0004639625549316406,
    0.00090789794921875,
    0.00030112266540527344,
    0.002341032028198242,
    0.0006153583526611328,
    0.00213623046875,
    0.0012068748474121094,
    0.0015838146209716797,
    0.0004627704620361328,
    0.0007872581481933594,
    0.0017769336700439453,
    0.0007169246673583984,
    0.00140380859375,
    0.000576019287109375,
    0.0004730224609375,
    0.0004532337188720703
  ],
  "board_states": [
    "#....##..\n#........\n#........\n#...XX...\n#........\n#........\n#...X....\n#...X....\n#........",
    "#....##..\n#........\n#.....O..\n#...XX...\n#........\n#........\n#...X....\n#...X....\n#........",
    "#....##..\n#........\n#.....O..\n#...XX...\n#........\n#........\n#...X.X..\n#...X....\n#........",
    "#....##..\n#........\n#.....O..\n#...XXO..\n#........\n#........\n#...X.X..\n#...X....\n#........",
    "#....##..\n#........\n#.....O..\n#...XXO..\n#.....X..\n#........\n#...X.X..\n#...X....\n#........",
    "#....##..\n#.....O..\n#.....O..\n#...XXO..\n#.....X..\n#........\n#...X.X..\n#...X....\n#........",
    "#....##..\n#...X.O..\n#.....O..\n#...XXO..\n#.....X..\n#........\n#...X.X..\n#...X....\n#........",
    "#....##..\n#...XOO..\n#.....O..\n#...XXO..\n#.....X..\n#........\n#...X.X..\n#...X....\n#........",
    "#....##..\n#...XOO..\n#.....O..\n#...XXOX.\n#.....X..\n#........\n#...X.X..\n#...X....\n#........",
    "#....##..\n#...XOO..\n#.....O..\n#...XXOX.\n#.....XO.\n#........\n#...X.X..\n#...X....\n#........",
    "#....##..\n#...XOO..\n#.....O..\n#...XXOX.\n#.....XOX\n#........\n#...X.X..\n#...X....\n#........",
    "#....##..\n#...XOO..\n#.....O..\n#...XXOX.\n#.....XOX\n#......O.\n#...X.X..\n#...X....\n#........",
    "#...X##..\n#...XOO..\n#.....O..\n#...XXOX.\n#.....XOX\n#......O.\n#...X.X..\n#...X....\n#........",
    "#...X##..\n#...XOO..\n#.....O..\n#...XXOX.\n#....OXOX\n#......O.\n#...X.X..\n#...X....\n#........",
    "#...X##..\n#...XOO..\n#.....O..\n#...XXOX.\n#....OXOX\n#.....XO.\n#...X.X..\n#...X....\n#........",
    "#...X##..\n#...XOO..\n#.....O..\n#...XXOX.\n#....OXOX\n#.....XOO\n#...X.X..\n#...X....\n#........",
    "#...X##..\n#...XOO..\n#.....O..\n#...XXOXX\n#....OXOX\n#.....XOO\n#...X.X..\n#...X....\n#........",
    "#...X##..\n#...XOO..\n#.....O..\n#...XXOXX\n#....OXOX\n#.....XOO\n#...X.X..\n#.O.X....\n#........",
    "#...X##..\n#...XOO..\n#.....O..\n#...XXOXX\n#....OXOX\n#.....XOO\n#...X.XX.\n#.O.X....\n#........",
    "#...X##..\n#...XOO..\n#.....O..\n#...XXOXX\n#....OXOX\n#...O.XOO\n#...X.XX.\n#.O.X....\n#........",
    "#...X##..\n#...XOO..\n#.....O..\n#...XXOXX\n#....OX.X\n#...O.X..\n#...X.XXX\n#.O.X....\n#........",
    "#...X##..\n#...XOO..\n#.....O..\n#...XXOXX\n#..O.OX.X\n#...O.X..\n#...X.XXX\n#.O.X....\n#........",
    "#...X##..\n#...XOO..\n#.....O..\n#...XXOXX\n#..O.OXXX\n#...O.X..\n#...X.XXX\n#.O.X....\n#........",
    "#...X##..\n#...XOO..\n#.....O..\n#..OXXOXX\n#..O.OXXX\n#...O.X..\n#...X.XXX\n#.O.X....\n#........",
    "#...X##..\n#...XOO..\n#..X..O..\n#..OXXOXX\n#..O.OXXX\n#...O.X..\n#...X.XXX\n#.O.X....\n#........",
    "#...X##..\n#...XOO..\n#.OX..O..\n#..OXXOXX\n#..O.OXXX\n#...O.X..\n#...X.XXX\n#.O.X....\n#........",
    "#...X##..\n#...XOO..\n#.OX..O..\n#.XOXXOXX\n#..O.OXXX\n#...O.X..\n#...X.XXX\n#.O.X....\n#........",
    "#...X##..\n#...XOO..\n#.OX..O..\n#.XOXXOXX\n#.OO.OXXX\n#...O.X..\n#...X.XXX\n#.O.X....\n#........",
    "#...X##..\n#...XOO..\n#.OX..O..\n#XXOXXOXX\n#.OO.OXXX\n#...O.X..\n#...X.XXX\n#.O.X....\n#........",
    "#...X##..\n#...XOO..\n#.OX..O..\n#XXOXXOXX\n#OOO.OXXX\n#...O.X..\n#...X.XXX\n#.O.X....\n#........",
    "#...X##..\n#...XOO..\n#XOX..O..\n#XXOXXOXX\n#OOO.OXXX\n#...O.X..\n#...X.XXX\n#.O.X....\n#........",
    "#...X##..\n#O..XOO..\n#.OX..O..\n#..OXXOXX\n#OOO.OXXX\n#...O.X..\n#...X.XXX\n#.O.X....\n#........",
    "#...X##..\n#O..XOO..\n#.OX..O..\n#..OXXOXX\n#OOO.OXXX\n#...O.X..\n#...XXXXX\n#.O.X....\n#........",
    "#...X##..\n#O..XOO..\n#.OX..O..\n#..OXXOXX\n#OOO.OXXX\n#O..O.X..\n#...XXXXX\n#.O.X....\n#........",
    "#...X##..\n#O..XOO..\n#.OX..O..\n#..OXXOXX\n#OOO.OXXX\n#O..O.X..\n#...XXXXX\n#.O.X....\n#...X....",
    "#...X##..\n#O..XOO..\n#.OX..O..\n#..OXXOXX\n#OOOOOXXX\n#O..O.X..\n#...XXXXX\n#.O.X....\n#...X....",
    "#...X##..\n#O..XOO..\n#.OX..O..\n#..OXXOXX\n#OOOOOXXX\n#O..O.X..\n#..XXXXXX\n#.O.X....\n#...X....",
    "#...X##..\n#O..XOO..\n#.OX.OO..\n#..OXXOXX\n#OOOOOXXX\n#O..O.X..\n#..XXXXXX\n#.O.X....\n#...X....",
    "#...X##..\n#O..XOO..\n#.OXXOO..\n#..OXXOXX\n#OOOOOXXX\n#O..O.X..\n#..XXXXXX\n#.O.X....\n#...X....",
    "#...X##..\n#O..XOO..\n#.OXXOO..\n#..OXXOXX\n#OOOOOXXX\n#O..O.X..\n#O.XXXXXX\n#.O.X....\n#...X....",
    "#...X##..\n#O..XOO..\n#.OXXOOX.\n#..OXXOXX\n#OOOOOXXX\n#O..O.X..\n#O.XXXXXX\n#.O.X....\n#...X....",
    "#...X##..\n#O..XOOO.\n#.OXXOOX.\n#..OXXOXX\n#OOOOOXXX\n#O..O.X..\n#O.XXXXXX\n#.O.X....\n#...X....",
    "#.X.X##..\n#O..XOOO.\n#.OXXOOX.\n#..OXXOXX\n#OOOOOXXX\n#O..O.X..\n#O.XXXXXX\n#.O.X....\n#...X....",
    "#.X.X##..\n#O..XOOOO\n#.OXXOOX.\n#..OXXOXX\n#OOOOOXXX\n#O..O.X..\n#O.XXXXXX\n#.O.X....\n#...X....",
    "#XX.X##..\n#O..XOOOO\n#.OXXOOX.\n#..OXXOXX\n#OOOOOXXX\n#O..O.X..\n#O.XXXXXX\n#.O.X....\n#...X....",
    "#XX.X##O.\n#O..XOOOO\n#.OXXOOX.\n#..OXXOXX\n#OOOOOXXX\n#O..O.X..\n#O.XXXXXX\n#.O.X....\n#...X....",
    "#XX.X##O.\n#O..XOOOO\n#.OXXOOX.\n#..OXXOXX\n#OOOOOXXX\n#O..O.X..\n#O.XXXXXX\n#XO.X....\n#...X....",
    "#XX.X##O.\n#O..XOOOO\n#.OXXOOX.\n#..OXXOXX\n#OOOOOXXX\n#O..O.X..\n#O.XXXXXX\n#.O.X....\n#O..X....",
    "#XX.X##O.\n#O..XOOOO\n#.OXXOOX.\n#..OXXOXX\n#OOOOOXXX\n#O..O.X..\n#O.XXXXXX\n#.O.X....\n#OX.X....",
    "#XX.X##O.\n#O..XOOOO\n#.OXXOOX.\n#..OXXOXX\n#OOOOOXXX\n#O..O.X..\n#O.XXXXXX\n#.O.X....\n#O.OX....",
    "#XX.X##O.\n#O..XOOOO\n#.OXXOOX.\n#..OXXOXX\n#OOOOOXXX\n#O..O.X..\n#O.XXXXXX\n#.OXX....\n#O.OX....",
    "#XX.X##O.\n#O..XOOOO\n#.OXXOOX.\n#..OXXOXX\n#OOOOOXXX\n#O..O.X..\n#O.XXXXXX\n#.OXX....\n#OOOX....",
    "#XX.X##O.\n#O..XOOOO\n#.OXXOOX.\n#..OXXOXX\n#OOOOOXXX\n#O.XO.X..\n#O.XXXXXX\n#.OXX....\n#OOOX....",
    "#XX.X##O.\n#O..XOOOO\n#.OXXOOX.\n#..OXXOXX\n#OOOOOXXX\n#O.XO.X..\n#OOXXXXXX\n#.OXX....\n#OOOX....",
    "#XXXX##O.\n#O..XOOOO\n#.OXXOOX.\n#..OXXOXX\n#OOOOOXXX\n#O.XO.X..\n#OOXXXXXX\n#.OXX....\n#OOOX....",
    "#XXXX##O.\n#O..XOOOO\n#.OXXOOX.\n#.OOXXOXX\n#OOOOOXXX\n#O.XO.X..\n#OOXXXXXX\n#.OXX....\n#OOOX....",
    "#XXXX##O.\n#OX.XOOOO\n#.OXXOOX.\n#.OOXXOXX\n#OOOOOXXX\n#O.XO.X..\n#OOXXXXXX\n#.OXX....\n#OOOX....",
    "#....##O.\n#O.O.OOOO\n#.O..OOX.\n#.OO..OXX\n#OOOOOXXX\n#O.XO.X..\n#OOXXXXXX\n#.OXX....\n#OOOX....",
    "#....##O.\n#O.O.OOOO\n#.O..OOXX\n#.OO..OXX\n#OOOOOXXX\n#O.XO.X..\n#OOXXXXXX\n#.OXX....\n#OOOX....",
    "#....##O.\n#OOO.OOOO\n#.O..OOXX\n#.OO..OXX\n#OOOOOXXX\n#O.XO.X..\n#OOXXXXXX\n#.OXX....\n#OOOX....",
    "#....##O.\n#OOO.OOOO\n#.O..OOXX\n#.OO..OXX\n#OOOOOXXX\n#OXXO.X..\n#OOXXXXXX\n#.OXX....\n#OOOX....",
    "#....##O.\n#OOOOOOOO\n#.O..OOXX\n#.OO..OXX\n#OOOOOXXX\n#OXXO.X..\n#OOXXXXXX\n#.OXX....\n#OOOX....",
    "#....##O.\n#OOOOOOOO\n#.O..OOXX\n#.OO..OXX\n#OOOOOXXX\n#OXXOXX..\n#OOXXXXXX\n#.OXX....\n#OOOX....",
    "#....##O.\n#OOOOOOOO\n#.O..OOXX\n#.OO..OXX\n#OOOOOXXX\n#OXXOXX..\n#OOXXXXXX\n#.OXX....\n#OOOX....",
    "#....##O.\n#OOOOOOOO\n#.O..OOXX\n#.OO..OXX\n#OOOOOXXX\n#OXXOXX..\n#OOXXXXXX\n#.OXX....\n#OOOX...."
  ],
  "final_result": "Player.black wins by 2.5"
}